anyfield.py
anyfield-0.3.1.dist-info/LICENSE
anyfield-0.3.1.dist-info/METADATA
anyfield-0.3.1.dist-info/WHEEL
anyfield-0.3.1.dist-info/top_level.txt
anyfield-0.3.1.dist-info/RECORD
